acapela.py
utils.py
acapela_downloader_py-0.1.7.dist-info/LICENSE
acapela_downloader_py-0.1.7.dist-info/METADATA
acapela_downloader_py-0.1.7.dist-info/WHEEL
acapela_downloader_py-0.1.7.dist-info/top_level.txt
acapela_downloader_py-0.1.7.dist-info/RECORD
