Metadata-Version: 2.1
Name: acapela-downloader-py
Version: 0.1.7
Summary: Acapela pwned but in Python.
Author: JWKK
Project-URL: Homepage, https://memerdev.com
Project-URL: GitHub, https://memerdev.com
Classifier: Programming Language :: Python :: 3
Classifier: Operating System :: OS Independent
Requires-Python: >=3.7
License-File: LICENSE
